{"gauge":{"lid":"WECC2","usgsId":"06701700","reachId":"191379","name":"West Creek (CO) at Westcreek","description":"","rfc":{"abbreviation":"MBRFC","name":"Missouri Basin River Forecast Center"},"wfo":{"abbreviation":"BOU","name":"Boulder"},"state":{"abbreviation":"CO","name":"Colorado"},"county":"Douglas","timeZone":"MST7MDT","latitude":39.1454,"longitude":-105.16,"pedts":{"observed":"HGIRG","forecast":""},"status":{"observed":{"primary":-999,"primaryUnit":"","secondary":-999,"secondaryUnit":"","floodCategory":"out_of_service","validTime":"0001-01-01T00:00:00Z"},"forecast":{"primary":-999,"primaryUnit":"","secondary":-999,"secondaryUnit":"","floodCategory":"out_of_service","validTime":"0001-01-01T00:00:00Z"}},"flood":{"stageUnits":"ft","flowUnits":"cfs","categories":{"major":{"stage":-9999,"flow":-9999},"moderate":{"stage":-9999,"flow":-9999},"minor":{"stage":-9999,"flow":-9999},"action":{"stage":-9999,"flow":344}},"lro":null,"crests":{"historic":[{"occurredTime":"2006-07-07T00:00:00Z","stage":9.55,"flow":2380,"preliminary":"O","olddatum":false},{"occurredTime":"2004-08-18T00:00:00Z","stage":6.47,"flow":332,"preliminary":"O","olddatum":false},{"occurredTime":"2003-08-31T00:00:00Z","stage":6.28,"flow":273,"preliminary":"O","olddatum":false},{"occurredTime":"2007-08-06T00:00:00Z","stage":5.97,"flow":143,"preliminary":"O","olddatum":false},{"occurredTime":"2015-05-13T00:00:00Z","stage":5.85,"flow":105,"preliminary":"O","olddatum":false},{"occurredTime":"2009-08-25T00:00:00Z","stage":5.8,"flow":91,"preliminary":"O","olddatum":false},{"occurredTime":"2016-05-06T00:00:00Z","stage":5.7,"flow":62,"preliminary":"O","olddatum":false},{"occurredTime":"2008-08-24T00:00:00Z","stage":5.69,"flow":62,"preliminary":"O","olddatum":false},{"occurredTime":"2018-07-23T00:00:00Z","stage":5.62,"flow":45,"preliminary":"O","olddatum":false},{"occurredTime":"2010-04-28T00:00:00Z","stage":5.6,"flow":40,"preliminary":"O","olddatum":false},{"occurredTime":"2011-08-04T00:00:00Z","stage":5.57,"flow":34,"preliminary":"O","olddatum":false},{"occurredTime":"2017-08-08T00:00:00Z","stage":5.56,"flow":31,"preliminary":"O","olddatum":false},{"occurredTime":"2005-04-20T00:00:00Z","stage":5.5,"flow":35,"preliminary":"O","olddatum":false},{"occurredTime":"2013-04-06T00:00:00Z","stage":5.49,"flow":20,"preliminary":"O","olddatum":false},{"occurredTime":"2014-05-26T00:00:00Z","stage":5.48,"flow":18,"preliminary":"O","olddatum":false},{"occurredTime":"2012-07-31T00:00:00Z","stage":5.42,"flow":10,"preliminary":"O","olddatum":false},{"occurredTime":"2019-04-10T00:00:00Z","stage":4.92,"flow":20,"preliminary":"O","olddatum":false},{"occurredTime":"2020-04-11T00:00:00Z","stage":4.13,"flow":13,"preliminary":"O","olddatum":false}],"recent":[{"occurredTime":"2020-04-11T00:00:00Z","stage":4.13,"flow":13,"preliminary":"O","olddatum":false},{"occurredTime":"2019-04-10T00:00:00Z","stage":4.92,"flow":20,"preliminary":"O","olddatum":false},{"occurredTime":"2018-07-23T00:00:00Z","stage":5.62,"flow":45,"preliminary":"O","olddatum":false},{"occurredTime":"2017-08-08T00:00:00Z","stage":5.56,"flow":31,"preliminary":"O","olddatum":false},{"occurredTime":"2016-05-06T00:00:00Z","stage":5.7,"flow":62,"preliminary":"O","olddatum":false},{"occurredTime":"2015-05-13T00:00:00Z","stage":5.85,"flow":105,"preliminary":"O","olddatum":false},{"occurredTime":"2014-05-26T00:00:00Z","stage":5.48,"flow":18,"preliminary":"O","olddatum":false},{"occurredTime":"2013-04-06T00:00:00Z","stage":5.49,"flow":20,"preliminary":"O","olddatum":false},{"occurredTime":"2012-07-31T00:00:00Z","stage":5.42,"flow":10,"preliminary":"O","olddatum":false},{"occurredTime":"2011-08-04T00:00:00Z","stage":5.57,"flow":34,"preliminary":"O","olddatum":false},{"occurredTime":"2010-04-28T00:00:00Z","stage":5.6,"flow":40,"preliminary":"O","olddatum":false},{"occurredTime":"2009-08-25T00:00:00Z","stage":5.8,"flow":91,"preliminary":"O","olddatum":false},{"occurredTime":"2008-08-24T00:00:00Z","stage":5.69,"flow":62,"preliminary":"O","olddatum":false},{"occurredTime":"2007-08-06T00:00:00Z","stage":5.97,"flow":143,"preliminary":"O","olddatum":false},{"occurredTime":"2006-07-07T00:00:00Z","stage":9.55,"flow":2380,"preliminary":"O","olddatum":false},{"occurredTime":"2005-04-20T00:00:00Z","stage":5.5,"flow":35,"preliminary":"O","olddatum":false},{"occurredTime":"2004-08-18T00:00:00Z","stage":6.47,"flow":332,"preliminary":"O","olddatum":false},{"occurredTime":"2003-08-31T00:00:00Z","stage":6.28,"flow":273,"preliminary":"O","olddatum":false}]},"lowWaters":{"historic":[]},"impacts":[{"stage":7,"statement":"WEST CREEK BACKS UP BEHIND CULVERTS UNDER WEST CREEK ROAD (ROAD TO THE TOWN OF WESTCREEK)."},{"stage":6.5,"statement":"WATER INTO LOW LYING AREAS ALONG WEST CREEK."}]},"images":{"probability":{"weekint":{"stage":"","flow":"","volume":""},"entperiod":{"stage":"","flow":"","volume":""},"shortrange":""},"hydrograph":{"default":"https://water.noaa.gov/resources/hydrographs/wecc2_hg.png","floodcat":"https://water.noaa.gov/resources/hydrographs/wecc2_record.png"},"photos":[]},"dataAttribution":[{"abbrev":"US Geological Survey","text":"USGS--Water Resources of the United States","title":"US Geological Survey","url":"http://waterdata.usgs.gov/co/nwis/uv/?site_no=06701700"},{"abbrev":"USGS","text":"06701700","title":"Observations courtesy of U.S. Geological Survey","url":"https://waterdata.usgs.gov/nwis/inventory/?site_no=06701700"}],"impactsLowWaters":[],"normalThreshold":null,"hydronotes":[{"statement":"Stage data may not be available during winter months.","effective":"1001","expiration":"0331"}],"datums":{"vertical":{"value":[]},"horizontal":{"value":[]},"notes":{"value":[]}},"inundation":{"enabled":false,"url":"","zeroDatum":null,"downloads":null,"siteSpecificInfo":"","dataAttribution":[]},"upstreamLid":"","downstreamLid":"SPTC2","inService":{"enabled":false,"message":"Gage is currently out of service."},"lowThreshold":null,"forecastReliability":"Forecasts are not available. Only observed stages are available for this point.","TruncateObs":"-1","TruncateFcst":"1","ObservedFloodCategory":"out_of_service","ForecastFloodCategory":"out_of_service"},"stageflow":{"observed":{"pedts":"","issuedTime":"0001-01-01T00:00:00Z","wfo":"","timeZone":"","primaryName":"","primaryUnits":"","secondaryName":"","secondaryUnits":"","data":[]},"forecast":{"pedts":"","issuedTime":"0001-01-01T00:00:00Z","wfo":"","timeZone":"","primaryName":"","primaryUnits":"","secondaryName":"","secondaryUnits":"","data":[]}},"modelGuidance":{},"availableSeries":[],"reachError":"HTTP 504 for https://api.water.noaa.gov/nwps/v1/reaches/191379/streamflow","generatedAt":"2026-05-01T12:33:03.029Z"}