{
  "id": "ca:01AF008",
  "key": "01AF008",
  "network": "ECCC",
  "country": "CA",
  "stationId": "01AF008",
  "name": "SAINT JOHN RIVER AT THE FALLS AT GRAND FALLS",
  "waterbody": "SAINT JOHN RIVER AT THE FALLS AT GRAND FALLS",
  "state": "NB",
  "latitude": 47.0513916015625,
  "longitude": -67.73860931396484,
  "forecast": false,
  "realtime": false,
  "noaaLid": null,
  "noaaForecast": false,
  "status": "Discontinued",
  "slug": "ca-01AF008",
  "noaaForecastPath": null,
  "generatedAt": "2026-05-01T12:10:11.451Z"
}