{
  "id": "ca:08NA008",
  "key": "08NA008",
  "network": "ECCC",
  "country": "CA",
  "stationId": "08NA008",
  "name": "KICKING HORSE RIVER AT NO. 2 TUNNEL",
  "waterbody": "KICKING HORSE RIVER AT NO. 2 TUNNEL",
  "state": "BC",
  "latitude": 51.43278121948242,
  "longitude": -116.39861297607422,
  "forecast": false,
  "realtime": false,
  "noaaLid": null,
  "noaaForecast": false,
  "status": "Discontinued",
  "slug": "ca-08NA008",
  "noaaForecastPath": null,
  "generatedAt": "2026-05-01T12:10:11.562Z"
}