{
  "id": "ca:02OD004",
  "key": "02OD004",
  "network": "ECCC",
  "country": "CA",
  "stationId": "02OD004",
  "name": "NICOLET SUD-OUEST (RIVIERE) A LA VISITATION",
  "waterbody": "NICOLET SUD-OUEST (RIVIERE) A LA VISITATION",
  "state": "QC",
  "latitude": 46.12971878051758,
  "longitude": -72.59583282470703,
  "forecast": false,
  "realtime": false,
  "noaaLid": null,
  "noaaForecast": false,
  "status": "Discontinued",
  "slug": "ca-02OD004",
  "noaaForecastPath": null,
  "generatedAt": "2026-05-01T12:10:11.475Z"
}