{
  "id": "ca:05BH011",
  "key": "05BH011",
  "network": "ECCC",
  "country": "CA",
  "stationId": "05BH011",
  "name": "JUMPINGPOUND CREEK AT BATEMAN'S RANCH",
  "waterbody": "JUMPINGPOUND CREEK AT BATEMAN'S RANCH",
  "state": "AB",
  "latitude": 51.02278137207031,
  "longitude": -114.61638641357422,
  "forecast": false,
  "realtime": false,
  "noaaLid": null,
  "noaaForecast": false,
  "status": "Discontinued",
  "slug": "ca-05BH011",
  "noaaForecastPath": null,
  "generatedAt": "2026-05-01T12:10:11.500Z"
}