{
  "id": "ca:08NM047",
  "key": "08NM047",
  "network": "ECCC",
  "country": "CA",
  "stationId": "08NM047",
  "name": "NASWHITO CREEK NEAR EWING'S LANDING",
  "waterbody": "NASWHITO CREEK NEAR EWING'S LANDING",
  "state": "BC",
  "latitude": 50.293060302734375,
  "longitude": -119.46111297607422,
  "forecast": false,
  "realtime": false,
  "noaaLid": null,
  "noaaForecast": false,
  "status": "Discontinued",
  "slug": "ca-08NM047",
  "noaaForecastPath": null,
  "generatedAt": "2026-05-01T12:10:11.578Z"
}