{
  "id": "ca:06DC001",
  "key": "06DC001",
  "network": "ECCC",
  "country": "CA",
  "stationId": "06DC001",
  "name": "WATHAMAN RIVER BELOW WATHAMAN LAKE",
  "waterbody": "WATHAMAN RIVER BELOW WATHAMAN LAKE",
  "state": "SK",
  "latitude": 57.08932876586914,
  "longitude": -103.70950317382812,
  "forecast": false,
  "realtime": true,
  "noaaLid": null,
  "noaaForecast": false,
  "status": "Active",
  "slug": "ca-06DC001",
  "noaaForecastPath": null,
  "generatedAt": "2026-05-01T12:10:11.534Z"
}