{
  "id": "ca:02NG006",
  "key": "02NG006",
  "network": "ECCC",
  "country": "CA",
  "stationId": "02NG006",
  "name": "SAINT-MAURICE (RIVIERE) A LA CENTRALE DE SHAWINIGAN",
  "waterbody": "SAINT-MAURICE (RIVIERE) A LA CENTRALE DE SHAWINIGAN",
  "state": "QC",
  "latitude": 46.53556060791016,
  "longitude": -72.76583099365234,
  "forecast": false,
  "realtime": false,
  "noaaLid": null,
  "noaaForecast": false,
  "status": "Discontinued",
  "slug": "ca-02NG006",
  "noaaForecastPath": null,
  "generatedAt": "2026-05-01T12:10:11.473Z"
}