{
  "id": "ca:08KE035",
  "key": "08KE035",
  "network": "ECCC",
  "country": "CA",
  "stationId": "08KE035",
  "name": "NARCOSLI CREEK ABOVE RAMSEY CREEK",
  "waterbody": "NARCOSLI CREEK ABOVE RAMSEY CREEK",
  "state": "BC",
  "latitude": 52.494998931884766,
  "longitude": -122.75582885742188,
  "forecast": false,
  "realtime": false,
  "noaaLid": null,
  "noaaForecast": false,
  "status": "Discontinued",
  "slug": "ca-08KE035",
  "noaaForecastPath": null,
  "generatedAt": "2026-05-01T12:10:11.552Z"
}