{
  "id": "ca:03OA009",
  "key": "03OA009",
  "network": "ECCC",
  "country": "CA",
  "stationId": "03OA009",
  "name": "HARRIE RIVER AT OUTLET OF HARRIE LAKE",
  "waterbody": "HARRIE RIVER AT OUTLET OF HARRIE LAKE",
  "state": "NL",
  "latitude": 52.93193817138672,
  "longitude": -66.92971801757812,
  "forecast": false,
  "realtime": false,
  "noaaLid": null,
  "noaaForecast": false,
  "status": "Discontinued",
  "slug": "ca-03OA009",
  "noaaForecastPath": null,
  "generatedAt": "2026-05-01T12:10:11.492Z"
}