{
  "id": "ca:05PG001",
  "key": "05PG001",
  "network": "ECCC",
  "country": "CA",
  "stationId": "05PG001",
  "name": "WHITESHELL RIVER AT OUTLET OF JESSICA LAKE",
  "waterbody": "WHITESHELL RIVER AT OUTLET OF JESSICA LAKE",
  "state": "MB",
  "latitude": 50.03491973876953,
  "longitude": -95.50666809082033,
  "forecast": false,
  "realtime": true,
  "noaaLid": null,
  "noaaForecast": false,
  "status": "Active",
  "slug": "ca-05PG001",
  "noaaForecastPath": null,
  "generatedAt": "2026-05-01T12:10:11.529Z"
}