{
  "id": "ca:08EE028",
  "key": "08EE028",
  "network": "ECCC",
  "country": "CA",
  "stationId": "08EE028",
  "name": "STATION CREEK ABOVE DIVERSIONS",
  "waterbody": "STATION CREEK ABOVE DIVERSIONS",
  "state": "BC",
  "latitude": 55.230281829833984,
  "longitude": -127.56749725341795,
  "forecast": false,
  "realtime": false,
  "noaaLid": null,
  "noaaForecast": false,
  "status": "Discontinued",
  "slug": "ca-08EE028",
  "noaaForecastPath": null,
  "generatedAt": "2026-05-01T12:10:11.544Z"
}