{
  "id": "ca:02PH010",
  "key": "02PH010",
  "network": "ECCC",
  "country": "CA",
  "stationId": "02PH010",
  "name": "DU SUD (RIVIERE) A 1,0 KM EN AMONT DU PONT-ROUTE A ARTHURVILLE",
  "waterbody": "DU SUD (RIVIERE) A 1,0 KM EN AMONT DU PONT-ROUTE A ARTHURVILLE",
  "state": "QC",
  "latitude": 46.820560455322266,
  "longitude": -70.75694274902344,
  "forecast": false,
  "realtime": true,
  "noaaLid": null,
  "noaaForecast": false,
  "status": "Active",
  "slug": "ca-02PH010",
  "noaaForecastPath": null,
  "generatedAt": "2026-05-01T12:10:11.483Z"
}