{
  "id": "ca:05BN003",
  "key": "05BN003",
  "network": "ECCC",
  "country": "CA",
  "stationId": "05BN003",
  "name": "EASTERN IRRIGATION DISTRICT WEST BANTRY CANAL NEAR HEADGATE",
  "waterbody": "EASTERN IRRIGATION DISTRICT WEST BANTRY CANAL NEAR HEADGATE",
  "state": "AB",
  "latitude": 50.53472137451172,
  "longitude": -111.81944274902344,
  "forecast": false,
  "realtime": false,
  "noaaLid": null,
  "noaaForecast": false,
  "status": "Discontinued",
  "slug": "ca-05BN003",
  "noaaForecastPath": null,
  "generatedAt": "2026-05-01T12:10:11.501Z"
}