{
  "id": "ca:02JE001",
  "key": "02JE001",
  "network": "ECCC",
  "country": "CA",
  "stationId": "02JE001",
  "name": "KIPAWA (RIVIERE) EN AVAL DU BARRAGE DE KIPAWA",
  "waterbody": "KIPAWA (RIVIERE) EN AVAL DU BARRAGE DE KIPAWA",
  "state": "QC",
  "latitude": 47.0494384765625,
  "longitude": -79.28666687011719,
  "forecast": false,
  "realtime": false,
  "noaaLid": null,
  "noaaForecast": false,
  "status": "Discontinued",
  "slug": "ca-02JE001",
  "noaaForecastPath": null,
  "generatedAt": "2026-05-01T12:10:11.468Z"
}