{
  "id": "ca:01CA005",
  "key": "01CA005",
  "network": "ECCC",
  "country": "CA",
  "stationId": "01CA005",
  "name": "MIMINEGASH RIVER AT ST. LAWRENCE",
  "waterbody": "MIMINEGASH RIVER AT ST. LAWRENCE",
  "state": "PE",
  "latitude": 46.848331451416016,
  "longitude": -64.1977767944336,
  "forecast": false,
  "realtime": false,
  "noaaLid": null,
  "noaaForecast": false,
  "status": "Discontinued",
  "slug": "ca-01CA005",
  "noaaForecastPath": null,
  "generatedAt": "2026-05-01T12:10:11.453Z"
}