{
  "id": "ca:02HC056",
  "key": "02HC056",
  "network": "ECCC",
  "country": "CA",
  "stationId": "02HC056",
  "name": "DON RIVER EAST BRANCH NEAR THORNHILL",
  "waterbody": "DON RIVER EAST BRANCH NEAR THORNHILL",
  "state": "ON",
  "latitude": 43.82661056518555,
  "longitude": -79.43807983398438,
  "forecast": false,
  "realtime": true,
  "noaaLid": null,
  "noaaForecast": false,
  "status": "Active",
  "slug": "ca-02HC056",
  "noaaForecastPath": null,
  "generatedAt": "2026-05-01T12:10:11.466Z"
}