{
  "id": "ca:08KE037",
  "key": "08KE037",
  "network": "ECCC",
  "country": "CA",
  "stationId": "08KE037",
  "name": "CUISSON CREEK (EAST FORK) ABOVE DAM",
  "waterbody": "CUISSON CREEK (EAST FORK) ABOVE DAM",
  "state": "BC",
  "latitude": 52.58110809326172,
  "longitude": -122.26917266845705,
  "forecast": false,
  "realtime": false,
  "noaaLid": null,
  "noaaForecast": false,
  "status": "Discontinued",
  "slug": "ca-08KE037",
  "noaaForecastPath": null,
  "generatedAt": "2026-05-01T12:10:11.552Z"
}