{
  "id": "ca:05TD001",
  "key": "05TD001",
  "network": "ECCC",
  "country": "CA",
  "stationId": "05TD001",
  "name": "GRASS RIVER ABOVE STANDING STONE FALLS",
  "waterbody": "GRASS RIVER ABOVE STANDING STONE FALLS",
  "state": "MB",
  "latitude": 55.74061965942383,
  "longitude": -97.0051727294922,
  "forecast": false,
  "realtime": true,
  "noaaLid": null,
  "noaaForecast": false,
  "status": "Active",
  "slug": "ca-05TD001",
  "noaaForecastPath": null,
  "generatedAt": "2026-05-01T12:10:11.531Z"
}