{
  "id": "ca:02OA034",
  "key": "02OA034",
  "network": "ECCC",
  "country": "CA",
  "stationId": "02OA034",
  "name": "CHATEAUGUAY (RIVIERE) A SAINTE-MARTINE",
  "waterbody": "CHATEAUGUAY (RIVIERE) A SAINTE-MARTINE",
  "state": "QC",
  "latitude": 45.25333023071289,
  "longitude": -73.80027770996094,
  "forecast": false,
  "realtime": false,
  "noaaLid": null,
  "noaaForecast": false,
  "status": "Discontinued",
  "slug": "ca-02OA034",
  "noaaForecastPath": null,
  "generatedAt": "2026-05-01T12:10:11.473Z"
}