{
  "id": "ca:07NA004",
  "key": "07NA004",
  "network": "ECCC",
  "country": "CA",
  "stationId": "07NA004",
  "name": "REVILLON COUPE BELOW RIVIERE DES ROCHERS",
  "waterbody": "REVILLON COUPE BELOW RIVIERE DES ROCHERS",
  "state": "AB",
  "latitude": 58.85277938842773,
  "longitude": -111.26943969726562,
  "forecast": false,
  "realtime": false,
  "noaaLid": null,
  "noaaForecast": false,
  "status": "Discontinued",
  "slug": "ca-07NA004",
  "noaaForecastPath": null,
  "generatedAt": "2026-05-01T12:10:11.541Z"
}