{
  "id": "ca:08LF062",
  "key": "08LF062",
  "network": "ECCC",
  "country": "CA",
  "stationId": "08LF062",
  "name": "BONAPARTE RIVER NEAR BRIDGE LAKE",
  "waterbody": "BONAPARTE RIVER NEAR BRIDGE LAKE",
  "state": "BC",
  "latitude": 51.3355598449707,
  "longitude": -120.7986068725586,
  "forecast": false,
  "realtime": false,
  "noaaLid": null,
  "noaaForecast": false,
  "status": "Discontinued",
  "slug": "ca-08LF062",
  "noaaForecastPath": null,
  "generatedAt": "2026-05-01T12:10:11.557Z"
}