{
  "id": "ca:03AC009",
  "key": "03AC009",
  "network": "ECCC",
  "country": "CA",
  "stationId": "03AC009",
  "name": "BELL (RIVIERE) A RAPIDES-DE-CEDRES",
  "waterbody": "BELL (RIVIERE) A RAPIDES-DE-CEDRES",
  "state": "QC",
  "latitude": 49.01082992553711,
  "longitude": -77.0633316040039,
  "forecast": false,
  "realtime": false,
  "noaaLid": null,
  "noaaForecast": false,
  "status": "Discontinued",
  "slug": "ca-03AC009",
  "noaaForecastPath": null,
  "generatedAt": "2026-05-01T12:10:11.489Z"
}