{
  "id": "usgs:03535400",
  "key": "03535400",
  "network": "USGS",
  "country": "US",
  "stationId": "03535400",
  "name": "BEAVER CREEK AT SOLWAY, TN",
  "waterbody": "BEAVER CREEK AT SOLWAY, TN",
  "state": "TN",
  "latitude": 35.96503044,
  "longitude": -84.1786528,
  "forecast": true,
  "realtime": true,
  "noaaLid": "SOLT1",
  "noaaForecast": true,
  "noaaWaterbody": "Beaver Creek (TN)",
  "noaaStatus": "not_defined",
  "noaaHydrographUrl": "https://water.noaa.gov/gauges/solt1",
  "slug": "usgs-03535400",
  "noaaForecastPath": "data/noaa-forecast/SOLT1.json",
  "generatedAt": "2026-05-01T12:10:11.387Z"
}