{
  "id": "usgs:07312200",
  "key": "07312200",
  "network": "USGS",
  "country": "US",
  "stationId": "07312200",
  "name": "Beaver Ck nr Electra, TX",
  "waterbody": "Beaver Ck nr Electra, TX",
  "state": "TX",
  "latitude": 33.90592785,
  "longitude": -98.9050666,
  "forecast": true,
  "realtime": true,
  "noaaLid": "ELTT2",
  "noaaForecast": true,
  "noaaWaterbody": "Beaver Creek (TX)",
  "noaaStatus": "no_flooding",
  "noaaHydrographUrl": "https://water.noaa.gov/gauges/eltt2",
  "slug": "usgs-07312200",
  "noaaForecastPath": "data/noaa-forecast/ELTT2.json",
  "generatedAt": "2026-05-01T12:10:11.388Z"
}