{
  "id": "usgs:142063391",
  "key": "142063391",
  "network": "USGS",
  "country": "US",
  "stationId": "142063391",
  "name": "ROCK CREEK NEAR BETHANY LAKE, NEAR BETHANY, OR",
  "waterbody": "ROCK CREEK NEAR BETHANY LAKE, NEAR BETHANY, OR",
  "state": "OR",
  "latitude": 45.55603056,
  "longitude": -122.874236,
  "forecast": false,
  "realtime": true,
  "noaaLid": null,
  "noaaForecast": false,
  "slug": "usgs-142063391",
  "noaaForecastPath": null,
  "generatedAt": "2026-05-01T12:10:11.348Z"
}