{
  "id": "usgs:0209691611",
  "key": "0209691611",
  "network": "USGS",
  "country": "US",
  "stationId": "0209691611",
  "name": "COLLINS CREEK AT HWY 54 NEAR WHITE CROSS, NC",
  "waterbody": "COLLINS CREEK AT HWY 54 NEAR WHITE CROSS, NC",
  "state": "NC",
  "latitude": 35.93163889,
  "longitude": -79.2058333,
  "forecast": false,
  "realtime": true,
  "noaaLid": null,
  "noaaForecast": false,
  "slug": "usgs-0209691611",
  "noaaForecastPath": null,
  "generatedAt": "2026-05-01T12:10:11.326Z"
}