{
  "id": "usgs:01018009",
  "key": "01018009",
  "network": "USGS",
  "country": "US",
  "stationId": "01018009",
  "name": "Pearce Brook at Route 1 at Houlton, Maine",
  "waterbody": "Pearce Brook at Route 1 at Houlton, Maine",
  "state": "ME",
  "latitude": 46.11527778,
  "longitude": -67.84027778,
  "forecast": true,
  "realtime": true,
  "noaaLid": "PEAM1",
  "noaaForecast": true,
  "noaaWaterbody": "Pearce Brook",
  "noaaStatus": "no_flooding",
  "noaaHydrographUrl": "https://water.noaa.gov/gauges/peam1",
  "slug": "usgs-01018009",
  "noaaForecastPath": "data/noaa-forecast/PEAM1.json",
  "generatedAt": "2026-05-01T12:10:11.256Z"
}