{
  "id": "usgs:12409000",
  "key": "12409000",
  "network": "USGS",
  "country": "US",
  "stationId": "12409000",
  "name": "COLVILLE RIVER AT KETTLE FALLS, WA",
  "waterbody": "COLVILLE RIVER AT KETTLE FALLS, WA",
  "state": "WA",
  "latitude": 48.5943461,
  "longitude": -118.0624887,
  "forecast": true,
  "realtime": true,
  "noaaLid": "KTFW1",
  "noaaForecast": true,
  "noaaWaterbody": "Colville River",
  "noaaStatus": "not_defined",
  "noaaHydrographUrl": "https://water.noaa.gov/gauges/ktfw1",
  "slug": "usgs-12409000",
  "noaaForecastPath": "data/noaa-forecast/KTFW1.json",
  "generatedAt": "2026-05-01T12:10:11.431Z"
}