{
  "id": "usgs:09491980",
  "key": "09491980",
  "network": "USGS",
  "country": "US",
  "stationId": "09491980",
  "name": "N-FORK WHITE RIVER BLW GOLD GULCH AT WHITERIVER AZ",
  "waterbody": "N-FORK WHITE RIVER BLW GOLD GULCH AT WHITERIVER AZ",
  "state": "AZ",
  "latitude": 33.87530556,
  "longitude": -109.9491944,
  "forecast": false,
  "realtime": true,
  "noaaLid": null,
  "noaaForecast": false,
  "slug": "usgs-09491980",
  "noaaForecastPath": null,
  "generatedAt": "2026-05-01T12:10:11.162Z"
}