{
  "id": "usgs:07377782",
  "key": "07377782",
  "network": "USGS",
  "country": "US",
  "stationId": "07377782",
  "name": "White Bayou SE of Zachary, LA",
  "waterbody": "White Bayou SE of Zachary, LA",
  "state": "LA",
  "latitude": 30.6371305,
  "longitude": -91.1276064,
  "forecast": true,
  "realtime": true,
  "noaaLid": "WBHL1",
  "noaaForecast": true,
  "noaaWaterbody": "White Bayou",
  "noaaStatus": "not_defined",
  "noaaHydrographUrl": "https://water.noaa.gov/gauges/wbhl1",
  "slug": "usgs-07377782",
  "noaaForecastPath": "data/noaa-forecast/WBHL1.json",
  "generatedAt": "2026-05-01T12:10:11.253Z"
}