{
  "id": "usgs:03184000",
  "key": "03184000",
  "network": "USGS",
  "country": "US",
  "stationId": "03184000",
  "name": "GREENBRIER RIVER AT HILLDALE, WV",
  "waterbody": "GREENBRIER RIVER AT HILLDALE, WV",
  "state": "WV",
  "latitude": 37.64012018,
  "longitude": -80.805083,
  "forecast": true,
  "realtime": true,
  "noaaLid": "HLLW2",
  "noaaForecast": true,
  "noaaWaterbody": "Greenbrier River",
  "noaaStatus": "no_flooding",
  "noaaHydrographUrl": "https://water.noaa.gov/gauges/hllw2",
  "slug": "usgs-03184000",
  "noaaForecastPath": "data/noaa-forecast/HLLW2.json",
  "generatedAt": "2026-05-01T12:10:11.435Z"
}