{
  "id": "usgs:04203983",
  "key": "04203983",
  "network": "USGS",
  "country": "US",
  "stationId": "04203983",
  "name": "Cuyahoga R at Gorge Metro Pk at Cuyahoga Falls OH",
  "waterbody": "Cuyahoga R at Gorge Metro Pk at Cuyahoga Falls OH",
  "state": "OH",
  "latitude": 41.12305556,
  "longitude": -81.4972222,
  "forecast": false,
  "realtime": true,
  "noaaLid": null,
  "noaaForecast": false,
  "slug": "usgs-04203983",
  "noaaForecastPath": null,
  "generatedAt": "2026-05-01T12:10:11.338Z"
}