{
  "id": "usgs:15310002",
  "key": "15310002",
  "network": "USGS",
  "country": "US",
  "stationId": "15310002",
  "name": "MOSQUITO FORK 2 MI BL KECHUMSTUK C NR CHICKEN AK",
  "waterbody": "MOSQUITO FORK 2 MI BL KECHUMSTUK C NR CHICKEN AK",
  "state": "AK",
  "latitude": 64.0344444,
  "longitude": -142.5283333,
  "forecast": false,
  "realtime": true,
  "noaaLid": null,
  "noaaForecast": false,
  "slug": "usgs-15310002",
  "noaaForecastPath": null,
  "generatedAt": "2026-05-01T12:10:11.157Z"
}