{
  "id": "usgs:02138816",
  "key": "02138816",
  "network": "USGS",
  "country": "US",
  "stationId": "02138816",
  "name": "OLD CATAWBA R BL CATAWBA DAM NEAR BRIDGEWATER, NC",
  "waterbody": "OLD CATAWBA R BL CATAWBA DAM NEAR BRIDGEWATER, NC",
  "state": "NC",
  "latitude": 35.7344861,
  "longitude": -81.887375,
  "forecast": false,
  "realtime": true,
  "noaaLid": null,
  "noaaForecast": false,
  "slug": "usgs-02138816",
  "noaaForecastPath": null,
  "generatedAt": "2026-05-01T12:10:11.328Z"
}