{
  "id": "usgs:04287000",
  "key": "04287000",
  "network": "USGS",
  "country": "US",
  "stationId": "04287000",
  "name": "DOG RIVER AT NORTHFIELD FALLS, VT",
  "waterbody": "DOG RIVER AT NORTHFIELD FALLS, VT",
  "state": "VT",
  "latitude": 44.1825606,
  "longitude": -72.6406655,
  "forecast": true,
  "realtime": true,
  "noaaLid": "NFFV1",
  "noaaForecast": true,
  "noaaWaterbody": "Dog River",
  "noaaStatus": "no_flooding",
  "noaaHydrographUrl": "https://water.noaa.gov/gauges/nffv1",
  "slug": "usgs-04287000",
  "noaaForecastPath": "data/noaa-forecast/NFFV1.json",
  "generatedAt": "2026-05-01T12:10:11.419Z"
}