{
  "id": "usgs:06755840",
  "key": "06755840",
  "network": "USGS",
  "country": "US",
  "stationId": "06755840",
  "name": "DIAMOND CR BEL ROUND TOP RD, AT F E WARREN AFB, WY",
  "waterbody": "DIAMOND CR BEL ROUND TOP RD, AT F E WARREN AFB, WY",
  "state": "WY",
  "latitude": 41.14387059,
  "longitude": -104.8799694,
  "forecast": false,
  "realtime": true,
  "noaaLid": null,
  "noaaForecast": false,
  "slug": "usgs-06755840",
  "noaaForecastPath": null,
  "generatedAt": "2026-05-01T12:10:11.446Z"
}