{"name": "ns1:timeSeriesResponseType", "declaredType": "org.cuahsi.waterml.TimeSeriesResponseType", "scope": "javax.xml.bind.JAXBElement$GlobalScope", "value": {"queryInfo": {"queryURL": "http://waterservices.usgs.gov/nwis/dv/format=json&sites=06295000&parameterCd=00060&startDT=2025-11-02&endDT=2026-04-30", "criteria": {"locationParam": "[ALL:06295000]", "variableParam": "[00060]", "timeParam": {"beginDateTime": "2025-11-02T00:00:00.000", "endDateTime": "2026-04-30T00:00:00.000"}, "parameter": []}, "note": [{"value": "[ALL:06295000]", "title": "filter:sites"}, {"value": "[mode=RANGE, modifiedSince=null] interval={INTERVAL[2025-11-02T00:00:00.000-04:00/2026-04-30T00:00:00.000-04:00]}", "title": "filter:timeRange"}, {"value": "methodIds=[ALL]", "title": "filter:methodId"}, {"value": "2026-05-01T16:10:11.671Z", "title": "requestDT"}, {"value": "3b31af60-4578-11f1-b4b1-005056beda50", "title": "requestId"}, {"value": "Provisional data are subject to revision. Go to http://waterdata.usgs.gov/nwis/help/?provisional for more information.", "title": "disclaimer"}, {"value": "caas01", "title": "server"}]}, "timeSeries": [{"sourceInfo": {"siteName": "Yellowstone River at Forsyth MT", "siteCode": [{"value": "06295000", "network": "NWIS", "agencyCode": "USGS"}], "timeZoneInfo": {"defaultTimeZone": {"zoneOffset": "-07:00", "zoneAbbreviation": "MST"}, "daylightSavingsTimeZone": {"zoneOffset": "-06:00", "zoneAbbreviation": "MDT"}, "siteUsesDaylightSavingsTime": true}, "geoLocation": {"geogLocation": {"srs": "EPSG:4326", "latitude": 46.266636, "longitude": -106.691303}, "localSiteXY": []}, "note": [], "siteType": [], "siteProperty": [{"value": "ST", "name": "siteTypeCd"}, {"value": "101000011202", "name": "hucCd"}, {"value": "30", "name": "stateCd"}, {"value": "30087", "name": "countyCd"}]}, "variable": {"variableCode": [{"value": "00060", "network": "NWIS", "vocabulary": "NWIS:UnitValues", "variableID": 45807197, "default": true}], "variableName": "Streamflow, ft&#179;/s", "variableDescription": "Discharge, cubic feet per second", "valueType": "Derived Value", "unit": {"unitCode": "ft3/s"}, "options": {"option": [{"value": "Mean", "name": "Statistic", "optionCode": "00003"}]}, "note": [], "noDataValue": -999999.0, "variableProperty": [], "oid": "45807197"}, "values": [{"value": [{"value": "5800", "qualifiers": ["A"], "dateTime": "2025-11-02T00:00:00.000"}, {"value": "5710", "qualifiers": ["A"], "dateTime": "2025-11-03T00:00:00.000"}, {"value": "5670", "qualifiers": ["A"], "dateTime": "2025-11-04T00:00:00.000"}, {"value": "5650", "qualifiers": ["A"], "dateTime": "2025-11-05T00:00:00.000"}, {"value": "5680", "qualifiers": ["A"], "dateTime": "2025-11-06T00:00:00.000"}, {"value": "5650", "qualifiers": ["A"], "dateTime": "2025-11-07T00:00:00.000"}, {"value": "5680", "qualifiers": ["A"], "dateTime": "2025-11-08T00:00:00.000"}, {"value": "5720", "qualifiers": ["A"], "dateTime": "2025-11-09T00:00:00.000"}, {"value": "5710", "qualifiers": ["A"], "dateTime": "2025-11-10T00:00:00.000"}, {"value": "5660", "qualifiers": ["A"], "dateTime": "2025-11-11T00:00:00.000"}, {"value": "5590", "qualifiers": ["A"], "dateTime": "2025-11-12T00:00:00.000"}, {"value": "5600", "qualifiers": ["A"], "dateTime": "2025-11-13T00:00:00.000"}, {"value": "5630", "qualifiers": ["A"], "dateTime": "2025-11-14T00:00:00.000"}, {"value": "5620", "qualifiers": ["A"], "dateTime": "2025-11-15T00:00:00.000"}, {"value": "5610", "qualifiers": ["A"], "dateTime": "2025-11-16T00:00:00.000"}, {"value": "5630", "qualifiers": ["A"], "dateTime": "2025-11-17T00:00:00.000"}, {"value": "5720", "qualifiers": ["A"], "dateTime": "2025-11-18T00:00:00.000"}, {"value": "5780", "qualifiers": ["A"], "dateTime": "2025-11-19T00:00:00.000"}, {"value": "5770", "qualifiers": ["P"], "dateTime": "2025-11-20T00:00:00.000"}, {"value": "5710", "qualifiers": ["P"], "dateTime": "2025-11-21T00:00:00.000"}, {"value": "5680", "qualifiers": ["P"], "dateTime": "2025-11-22T00:00:00.000"}, {"value": "5670", "qualifiers": ["P"], "dateTime": "2025-11-23T00:00:00.000"}, {"value": "5640", "qualifiers": ["P"], "dateTime": "2025-11-24T00:00:00.000"}, {"value": "5590", "qualifiers": ["P"], "dateTime": "2025-11-25T00:00:00.000"}, {"value": "5610", "qualifiers": ["P"], "dateTime": "2025-11-26T00:00:00.000"}, {"value": "5630", "qualifiers": ["P"], "dateTime": "2025-11-27T00:00:00.000"}, {"value": "5590", "qualifiers": ["P"], "dateTime": "2025-11-28T00:00:00.000"}, {"value": "5500", "qualifiers": ["P"], "dateTime": "2025-11-29T00:00:00.000"}, {"value": "-999999", "qualifiers": ["P", "Ice"], "dateTime": "2025-11-30T00:00:00.000"}, {"value": "-999999", "qualifiers": ["P", "Ice"], "dateTime": "2025-12-01T00:00:00.000"}, {"value": "-999999", "qualifiers": ["P", "Ice"], "dateTime": "2025-12-02T00:00:00.000"}, {"value": "-999999", "qualifiers": ["P", "Ice"], "dateTime": "2025-12-03T00:00:00.000"}, {"value": "-999999", "qualifiers": ["P", "Ice"], "dateTime": "2025-12-04T00:00:00.000"}, {"value": "-999999", "qualifiers": ["P", "Ice"], "dateTime": "2025-12-05T00:00:00.000"}, {"value": "5620", "qualifiers": ["P"], "dateTime": "2025-12-06T00:00:00.000"}, {"value": "5500", "qualifiers": ["P"], "dateTime": "2025-12-07T00:00:00.000"}, {"value": "5600", "qualifiers": ["P"], "dateTime": "2025-12-08T00:00:00.000"}, {"value": "5640", "qualifiers": ["P"], "dateTime": "2025-12-09T00:00:00.000"}, {"value": "5630", "qualifiers": ["P"], "dateTime": "2025-12-10T00:00:00.000"}, {"value": "5590", "qualifiers": ["P"], "dateTime": "2025-12-11T00:00:00.000"}, {"value": "-999999", "qualifiers": ["P", "Ice"], "dateTime": "2025-12-12T00:00:00.000"}, {"value": "-999999", "qualifiers": ["P", "Ice"], "dateTime": "2025-12-13T00:00:00.000"}, {"value": "-999999", "qualifiers": ["P", "Ice"], "dateTime": "2025-12-14T00:00:00.000"}, {"value": "-999999", "qualifiers": ["P", "Ice"], "dateTime": "2025-12-15T00:00:00.000"}, {"value": "-999999", "qualifiers": ["P", "Ice"], "dateTime": "2025-12-16T00:00:00.000"}, {"value": "-999999", "qualifiers": ["P", "Ice"], "dateTime": "2025-12-17T00:00:00.000"}, {"value": "-999999", "qualifiers": ["P", "Ice"], "dateTime": "2025-12-18T00:00:00.000"}, {"value": "-999999", "qualifiers": ["P", "Ice"], "dateTime": "2025-12-19T00:00:00.000"}, {"value": "5820", "qualifiers": ["P"], "dateTime": "2025-12-20T00:00:00.000"}, {"value": "5690", "qualifiers": ["P"], "dateTime": "2025-12-21T00:00:00.000"}, {"value": "5570", "qualifiers": ["P"], "dateTime": "2025-12-22T00:00:00.000"}, {"value": "5600", "qualifiers": ["P"], "dateTime": "2025-12-23T00:00:00.000"}, {"value": "5550", "qualifiers": ["P"], "dateTime": "2025-12-24T00:00:00.000"}, {"value": "5850", "qualifiers": ["P"], "dateTime": "2025-12-25T00:00:00.000"}, {"value": "6160", "qualifiers": ["P"], "dateTime": "2025-12-26T00:00:00.000"}, {"value": "6160", "qualifiers": ["P"], "dateTime": "2025-12-27T00:00:00.000"}, {"value": "-999999", "qualifiers": ["P", "Ice"], "dateTime": "2025-12-28T00:00:00.000"}, {"value": "-999999", "qualifiers": ["P", "Ice"], "dateTime": "2025-12-29T00:00:00.000"}, {"value": "-999999", "qualifiers": ["P", "Ice"], "dateTime": "2025-12-30T00:00:00.000"}, {"value": "-999999", "qualifiers": ["P", "Ice"], "dateTime": "2025-12-31T00:00:00.000"}, {"value": "-999999", "qualifiers": ["P", "Ice"], "dateTime": "2026-01-01T00:00:00.000"}, {"value": "-999999", "qualifiers": ["P", "Ice"], "dateTime": "2026-01-02T00:00:00.000"}, {"value": "5850", "qualifiers": ["P"], "dateTime": "2026-01-03T00:00:00.000"}, {"value": "5870", "qualifiers": ["P"], "dateTime": "2026-01-04T00:00:00.000"}, {"value": "5870", "qualifiers": ["P"], "dateTime": "2026-01-05T00:00:00.000"}, {"value": "5880", "qualifiers": ["P"], "dateTime": "2026-01-06T00:00:00.000"}, {"value": "5730", "qualifiers": ["P"], "dateTime": "2026-01-07T00:00:00.000"}, {"value": "5620", "qualifiers": ["P"], "dateTime": "2026-01-08T00:00:00.000"}, {"value": "5490", "qualifiers": ["P"], "dateTime": "2026-01-09T00:00:00.000"}, {"value": "5240", "qualifiers": ["P"], "dateTime": "2026-01-10T00:00:00.000"}, {"value": "5010", "qualifiers": ["P"], "dateTime": "2026-01-11T00:00:00.000"}, {"value": "4850", "qualifiers": ["P"], "dateTime": "2026-01-12T00:00:00.000"}, {"value": "4930", "qualifiers": ["P"], "dateTime": "2026-01-13T00:00:00.000"}, {"value": "5000", "qualifiers": ["P"], "dateTime": "2026-01-14T00:00:00.000"}, {"value": "5170", "qualifiers": ["P"], "dateTime": "2026-01-15T00:00:00.000"}, {"value": "5150", "qualifiers": ["P"], "dateTime": "2026-01-16T00:00:00.000"}, {"value": "-999999", "qualifiers": ["P", "Ice"], "dateTime": "2026-01-17T00:00:00.000"}, {"value": "-999999", "qualifiers": ["P", "Ice"], "dateTime": "2026-01-18T00:00:00.000"}, {"value": "-999999", "qualifiers": ["P", "Ice"], "dateTime": "2026-01-19T00:00:00.000"}, {"value": "-999999", "qualifiers": ["P", "Ice"], "dateTime": "2026-01-20T00:00:00.000"}, {"value": "-999999", "qualifiers": ["P", "Ice"], "dateTime": "2026-01-21T00:00:00.000"}, {"value": "-999999", "qualifiers": ["P", "Ice"], "dateTime": "2026-01-22T00:00:00.000"}, {"value": "-999999", "qualifiers": ["P", "Ice"], "dateTime": "2026-01-23T00:00:00.000"}, {"value": "-999999", "qualifiers": ["P", "Ice"], "dateTime": "2026-01-24T00:00:00.000"}, {"value": "-999999", "qualifiers": ["P", "Ice"], "dateTime": "2026-01-25T00:00:00.000"}, {"value": "-999999", "qualifiers": ["P", "Ice"], "dateTime": "2026-01-26T00:00:00.000"}, {"value": "-999999", "qualifiers": ["P", "Ice"], "dateTime": "2026-01-27T00:00:00.000"}, {"value": "-999999", "qualifiers": ["P", "Ice"], "dateTime": "2026-01-28T00:00:00.000"}, {"value": "-999999", "qualifiers": ["P", "Ice"], "dateTime": "2026-01-29T00:00:00.000"}, {"value": "-999999", "qualifiers": ["P", "Ice"], "dateTime": "2026-01-30T00:00:00.000"}, {"value": "-999999", "qualifiers": ["P", "Ice"], "dateTime": "2026-01-31T00:00:00.000"}, {"value": "-999999", "qualifiers": ["P", "Ice"], "dateTime": "2026-02-01T00:00:00.000"}, {"value": "-999999", "qualifiers": ["P", "Ice"], "dateTime": "2026-02-02T00:00:00.000"}, {"value": "-999999", "qualifiers": ["P", "Ice"], "dateTime": "2026-02-03T00:00:00.000"}, {"value": "-999999", "qualifiers": ["P", "Ice"], "dateTime": "2026-02-04T00:00:00.000"}, {"value": "-999999", "qualifiers": ["P", "Ice"], "dateTime": "2026-02-05T00:00:00.000"}, {"value": "-999999", "qualifiers": ["P", "Ice"], "dateTime": "2026-02-06T00:00:00.000"}, {"value": "4860", "qualifiers": ["P"], "dateTime": "2026-02-07T00:00:00.000"}, {"value": "4830", "qualifiers": ["P"], "dateTime": "2026-02-08T00:00:00.000"}, {"value": "4910", "qualifiers": ["P"], "dateTime": "2026-02-09T00:00:00.000"}, {"value": "4910", "qualifiers": ["P"], "dateTime": "2026-02-10T00:00:00.000"}, {"value": "4830", "qualifiers": ["P"], "dateTime": "2026-02-11T00:00:00.000"}, {"value": "4850", "qualifiers": ["P"], "dateTime": "2026-02-12T00:00:00.000"}, {"value": "4790", "qualifiers": ["P"], "dateTime": "2026-02-13T00:00:00.000"}, {"value": "4710", "qualifiers": ["P"], "dateTime": "2026-02-14T00:00:00.000"}, {"value": "4740", "qualifiers": ["P"], "dateTime": "2026-02-15T00:00:00.000"}, {"value": "4800", "qualifiers": ["P"], "dateTime": "2026-02-16T00:00:00.000"}, {"value": "4800", "qualifiers": ["P"], "dateTime": "2026-02-17T00:00:00.000"}, {"value": "4760", "qualifiers": ["P"], "dateTime": "2026-02-18T00:00:00.000"}, {"value": "-999999", "qualifiers": ["P", "Ice"], "dateTime": "2026-02-19T00:00:00.000"}, {"value": "-999999", "qualifiers": ["P", "Ice"], "dateTime": "2026-02-20T00:00:00.000"}, {"value": "-999999", "qualifiers": ["P", "Ice"], "dateTime": "2026-02-21T00:00:00.000"}, {"value": "-999999", "qualifiers": ["P", "Ice"], "dateTime": "2026-02-22T00:00:00.000"}, {"value": "-999999", "qualifiers": ["P", "Ice"], "dateTime": "2026-02-23T00:00:00.000"}, {"value": "-999999", "qualifiers": ["P", "Ice"], "dateTime": "2026-02-24T00:00:00.000"}, {"value": "-999999", "qualifiers": ["P", "Ice"], "dateTime": "2026-02-25T00:00:00.000"}, {"value": "-999999", "qualifiers": ["P", "Ice"], "dateTime": "2026-02-26T00:00:00.000"}, {"value": "5120", "qualifiers": ["P"], "dateTime": "2026-02-27T00:00:00.000"}, {"value": "5060", "qualifiers": ["P"], "dateTime": "2026-02-28T00:00:00.000"}, {"value": "5050", "qualifiers": ["P"], "dateTime": "2026-03-01T00:00:00.000"}, {"value": "4940", "qualifiers": ["P"], "dateTime": "2026-03-02T00:00:00.000"}, {"value": "4900", "qualifiers": ["P"], "dateTime": "2026-03-03T00:00:00.000"}, {"value": "4930", "qualifiers": ["P"], "dateTime": "2026-03-04T00:00:00.000"}, {"value": "4870", "qualifiers": ["P"], "dateTime": "2026-03-05T00:00:00.000"}, {"value": "4930", "qualifiers": ["P"], "dateTime": "2026-03-06T00:00:00.000"}, {"value": "4930", "qualifiers": ["P"], "dateTime": "2026-03-07T00:00:00.000"}, {"value": "4910", "qualifiers": ["P"], "dateTime": "2026-03-08T00:00:00.000"}, {"value": "4900", "qualifiers": ["P"], "dateTime": "2026-03-09T00:00:00.000"}, {"value": "4840", "qualifiers": ["P"], "dateTime": "2026-03-10T00:00:00.000"}, {"value": "4740", "qualifiers": ["P"], "dateTime": "2026-03-11T00:00:00.000"}, {"value": "4820", "qualifiers": ["P"], "dateTime": "2026-03-12T00:00:00.000"}, {"value": "4890", "qualifiers": ["P"], "dateTime": "2026-03-13T00:00:00.000"}, {"value": "5120", "qualifiers": ["P"], "dateTime": "2026-03-14T00:00:00.000"}, {"value": "4970", "qualifiers": ["P"], "dateTime": "2026-03-15T00:00:00.000"}, {"value": "5040", "qualifiers": ["P"], "dateTime": "2026-03-16T00:00:00.000"}, {"value": "5090", "qualifiers": ["P"], "dateTime": "2026-03-17T00:00:00.000"}, {"value": "5400", "qualifiers": ["P"], "dateTime": "2026-03-18T00:00:00.000"}, {"value": "5300", "qualifiers": ["P"], "dateTime": "2026-03-19T00:00:00.000"}, {"value": "5370", "qualifiers": ["P"], "dateTime": "2026-03-20T00:00:00.000"}, {"value": "5350", "qualifiers": ["P"], "dateTime": "2026-03-21T00:00:00.000"}, {"value": "5370", "qualifiers": ["P"], "dateTime": "2026-03-22T00:00:00.000"}, {"value": "5650", "qualifiers": ["P", "e"], "dateTime": "2026-03-23T00:00:00.000"}, {"value": "6290", "qualifiers": ["P"], "dateTime": "2026-03-24T00:00:00.000"}, {"value": "6720", "qualifiers": ["P"], "dateTime": "2026-03-25T00:00:00.000"}, {"value": "6510", "qualifiers": ["P"], "dateTime": "2026-03-26T00:00:00.000"}, {"value": "6240", "qualifiers": ["P"], "dateTime": "2026-03-27T00:00:00.000"}, {"value": "6670", "qualifiers": ["P"], "dateTime": "2026-03-28T00:00:00.000"}, {"value": "7770", "qualifiers": ["P"], "dateTime": "2026-03-29T00:00:00.000"}, {"value": "7700", "qualifiers": ["P", "e"], "dateTime": "2026-03-30T00:00:00.000"}, {"value": "7580", "qualifiers": ["P"], "dateTime": "2026-03-31T00:00:00.000"}, {"value": "7770", "qualifiers": ["P"], "dateTime": "2026-04-01T00:00:00.000"}, {"value": "8250", "qualifiers": ["P"], "dateTime": "2026-04-02T00:00:00.000"}, {"value": "8430", "qualifiers": ["P"], "dateTime": "2026-04-03T00:00:00.000"}, {"value": "8450", "qualifiers": ["P"], "dateTime": "2026-04-04T00:00:00.000"}, {"value": "8920", "qualifiers": ["P", "e"], "dateTime": "2026-04-05T00:00:00.000"}, {"value": "8810", "qualifiers": ["P", "e"], "dateTime": "2026-04-06T00:00:00.000"}, {"value": "8470", "qualifiers": ["P", "e"], "dateTime": "2026-04-07T00:00:00.000"}, {"value": "8190", "qualifiers": ["P"], "dateTime": "2026-04-08T00:00:00.000"}, {"value": "8270", "qualifiers": ["P"], "dateTime": "2026-04-09T00:00:00.000"}, {"value": "7870", "qualifiers": ["P", "e"], "dateTime": "2026-04-10T00:00:00.000"}, {"value": "8180", "qualifiers": ["P", "e"], "dateTime": "2026-04-11T00:00:00.000"}, {"value": "8520", "qualifiers": ["P", "e"], "dateTime": "2026-04-12T00:00:00.000"}, {"value": "8830", "qualifiers": ["P", "e"], "dateTime": "2026-04-13T00:00:00.000"}, {"value": "9200", "qualifiers": ["P", "e"], "dateTime": "2026-04-14T00:00:00.000"}, {"value": "9290", "qualifiers": ["P"], "dateTime": "2026-04-15T00:00:00.000"}, {"value": "8890", "qualifiers": ["P"], "dateTime": "2026-04-16T00:00:00.000"}, {"value": "8410", "qualifiers": ["P"], "dateTime": "2026-04-17T00:00:00.000"}, {"value": "8020", "qualifiers": ["P"], "dateTime": "2026-04-18T00:00:00.000"}, {"value": "7850", "qualifiers": ["P"], "dateTime": "2026-04-19T00:00:00.000"}, {"value": "7440", "qualifiers": ["P"], "dateTime": "2026-04-20T00:00:00.000"}, {"value": "6900", "qualifiers": ["P"], "dateTime": "2026-04-21T00:00:00.000"}, {"value": "6940", "qualifiers": ["P"], "dateTime": "2026-04-22T00:00:00.000"}, {"value": "6790", "qualifiers": ["P"], "dateTime": "2026-04-23T00:00:00.000"}, {"value": "7170", "qualifiers": ["P"], "dateTime": "2026-04-24T00:00:00.000"}, {"value": "8190", "qualifiers": ["P"], "dateTime": "2026-04-25T00:00:00.000"}, {"value": "8540", "qualifiers": ["P"], "dateTime": "2026-04-26T00:00:00.000"}, {"value": "8350", "qualifiers": ["P"], "dateTime": "2026-04-27T00:00:00.000"}, {"value": "7950", "qualifiers": ["P"], "dateTime": "2026-04-28T00:00:00.000"}, {"value": "7550", "qualifiers": ["P"], "dateTime": "2026-04-29T00:00:00.000"}, {"value": "7400", "qualifiers": ["P"], "dateTime": "2026-04-30T00:00:00.000"}], "qualifier": [{"qualifierCode": "Ice", "qualifierDescription": "Value is affected by ice at the measurement site.", "qualifierID": 0, "network": "NWIS", "vocabulary": "uv_rmk_cd"}, {"qualifierCode": "e", "qualifierDescription": "Value has been estimated.", "qualifierID": 1, "network": "NWIS", "vocabulary": "uv_rmk_cd"}, {"qualifierCode": "A", "qualifierDescription": "Approved for publication -- Processing and review completed.", "qualifierID": 2, "network": "NWIS", "vocabulary": "uv_rmk_cd"}, {"qualifierCode": "P", "qualifierDescription": "Provisional data subject to revision.", "qualifierID": 3, "network": "NWIS", "vocabulary": "uv_rmk_cd"}], "qualityControlLevel": [], "method": [{"methodDescription": "", "methodID": 81626}], "source": [], "offset": [], "sample": [], "censorCode": []}], "name": "USGS:06295000:00060:00003"}]}, "nil": false, "globalScope": true, "typeSubstituted": false}